django_any/__init__.py
django_any/forms.py
django_any/functions.py
django_any/models.py
django_any/test.py
django_any/xunit.py
django_any/contrib/__init__.py
django_any/contrib/auth.py
django_any/contrib/default.py
django_whatever-0.3.1.dist-info/AUTHORS
django_whatever-0.3.1.dist-info/LICENSE
django_whatever-0.3.1.dist-info/METADATA
django_whatever-0.3.1.dist-info/WHEEL
django_whatever-0.3.1.dist-info/top_level.txt
django_whatever-0.3.1.dist-info/RECORD
